adcm_pytest_plugin/__init__.py
adcm_pytest_plugin/common.py
adcm_pytest_plugin/custom_types.py
adcm_pytest_plugin/docker_utils.py
adcm_pytest_plugin/fixtures.py
adcm_pytest_plugin/params.py
adcm_pytest_plugin/plugin.py
adcm_pytest_plugin/utils.py
adcm_pytest_plugin/common_data/cluster_to_import/config.yaml
adcm_pytest_plugin/common_data/cluster_with_service/config.yaml
adcm_pytest_plugin/common_data/cluster_with_service/dummy_action.yaml
adcm_pytest_plugin/common_data/provider/config.yaml
adcm_pytest_plugin/common_data/provider/dummy_action.yaml
adcm_pytest_plugin/exceptions/__init__.py
adcm_pytest_plugin/exceptions/adcm.py
adcm_pytest_plugin/exceptions/bundles.py
adcm_pytest_plugin/exceptions/infrastructure.py
adcm_pytest_plugin/objects/__init__.py
adcm_pytest_plugin/objects/actions.py
adcm_pytest_plugin/steps/__init__.py
adcm_pytest_plugin/steps/actions.py
adcm_pytest_plugin/steps/asserts.py
adcm_pytest_plugin/steps/commands.py
adcm_pytest_plugin/steps/common.py
adcm_pytest_plugin-4.24.0.dist-info/LICENSE
adcm_pytest_plugin-4.24.0.dist-info/METADATA
adcm_pytest_plugin-4.24.0.dist-info/WHEEL
adcm_pytest_plugin-4.24.0.dist-info/entry_points.txt
adcm_pytest_plugin-4.24.0.dist-info/top_level.txt
adcm_pytest_plugin-4.24.0.dist-info/RECORD
