Metadata-Version: 2.1
Name: adcm-pytest-plugin
Version: 4.24.0
Summary: The pytest plugin including a set of common tools for ADCM testing
Home-page: UNKNOWN
Author: UNKNOWN
Author-email: UNKNOWN
License: UNKNOWN
Platform: UNKNOWN
Classifier: Framework :: Pytest
Requires-Dist: pytest (~=7.1)
Requires-Dist: docker (>=5.0.0)
Requires-Dist: adcm-client (>=adcm_client-2022.6.2.8)
Requires-Dist: allure-pytest (>=2.9.42)
Requires-Dist: requests
Requires-Dist: version-utils
Requires-Dist: ifaddr
Requires-Dist: retry
Requires-Dist: deprecated
Requires-Dist: coreapi
